yangsuite_yangtree-2.1.12.dist-info/licenses/LICENSE.txt
ysyangtree/__init__.py
ysyangtree/_version.py
ysyangtree/admin.py
ysyangtree/apps.py
ysyangtree/context.py
ysyangtree/models.py
ysyangtree/prevtest_utils.py
ysyangtree/tasks.py
ysyangtree/urls.py
ysyangtree/utilities.py
ysyangtree/yangsettree.py
ysyangtree/ymodels.py
ysyangtree/static/ysyangtree/css/chosen-cui.css
ysyangtree/static/ysyangtree/css/yangtree.css
ysyangtree/static/ysyangtree/css/chosen/chosen-sprite.png
ysyangtree/static/ysyangtree/css/chosen/chosen-sprite@2x.png
ysyangtree/static/ysyangtree/css/chosen/chosen.css
ysyangtree/static/ysyangtree/css/chosen/chosen.min.css
ysyangtree/static/ysyangtree/docs/.buildinfo
ysyangtree/static/ysyangtree/docs/environment.pickle
ysyangtree/static/ysyangtree/docs/explore.fjson
ysyangtree/static/ysyangtree/docs/explore.html
ysyangtree/static/ysyangtree/docs/genindex.fjson
ysyangtree/static/ysyangtree/docs/genindex.html
ysyangtree/static/ysyangtree/docs/globalcontext.json
ysyangtree/static/ysyangtree/docs/index.fjson
ysyangtree/static/ysyangtree/docs/index.html
ysyangtree/static/ysyangtree/docs/last_build
ysyangtree/static/ysyangtree/docs/objects.inv
ysyangtree/static/ysyangtree/docs/search.fjson
ysyangtree/static/ysyangtree/docs/search.html
ysyangtree/static/ysyangtree/docs/searchindex.js
ysyangtree/static/ysyangtree/docs/searchindex.json
ysyangtree/static/ysyangtree/docs/.doctrees/environment.pickle
ysyangtree/static/ysyangtree/docs/.doctrees/explore.doctree
ysyangtree/static/ysyangtree/docs/.doctrees/index.doctree
ysyangtree/static/ysyangtree/docs/_images/context-menu.png
ysyangtree/static/ysyangtree/docs/_images/module-text.png
ysyangtree/static/ysyangtree/docs/_images/yangtree.png
ysyangtree/static/ysyangtree/docs/_sources/explore.rst.txt
ysyangtree/static/ysyangtree/docs/_sources/index.rst.txt
ysyangtree/static/ysyangtree/docs/_static/basic.css
ysyangtree/static/ysyangtree/docs/_static/doctools.js
ysyangtree/static/ysyangtree/docs/_static/documentation_options.js
ysyangtree/static/ysyangtree/docs/_static/file.png
yangsuite_yangtree-2.1.12.dist-info/METADATA
yangsuite_yangtree-2.1.12.dist-info/WHEEL
yangsuite_yangtree-2.1.12.dist-info/entry_points.txt
yangsuite_yangtree-2.1.12.dist-info/top_level.txt
yangsuite_yangtree-2.1.12.dist-info/RECORD
