Metadata-Version: 2.4
Name: yangsuite-yangtree
Version: 2.1.12
Summary: YANG model loading, validation, and display for YANG Suite.
Home-page: https://developer.cisco.com
Author: Michael Ott
Author-email: miott@cisco.com
License: Cisco End User License Agreement
Requires-Python: >=3.6
License-File: LICENSE.txt
Requires-Dist: yangsuite>=3.0.0
Requires-Dist: yangsuite-devices>=2.0.0
Requires-Dist: yangsuite-filemanager>=1.5.0
Dynamic: author
Dynamic: author-email
Dynamic: description
Dynamic: home-page
Dynamic: license
Dynamic: license-file
Dynamic: requires-dist
Dynamic: requires-python
Dynamic: summary
